verify_x509/__init__.py
verify_x509/version.py
verify_x509-0.0.1.dist-info/LICENSE
verify_x509-0.0.1.dist-info/METADATA
verify_x509-0.0.1.dist-info/NOTICE
verify_x509-0.0.1.dist-info/WHEEL
verify_x509-0.0.1.dist-info/top_level.txt
verify_x509-0.0.1.dist-info/RECORD
