Metadata-Version: 2.1
Name: verify-x509
Version: 0.0.1
Summary: A minimalistic X.509 certificate validator
Home-page: https://github.com/pyauth/verify-x509
Author: Andrey Kislyuk
Author-email: kislyuk@gmail.com
License: Apache Software License
Project-URL: Documentation, https://pyauth.github.io/verify-x509/
Project-URL: Change log, https://github.com/pyauth/verify-x509/blob/main/Changes.rst
Project-URL: Issue tracker, https://github.com/pyauth/verify-x509/issues
Platform: MacOS X
Platform: Posix
Classifier: Intended Audience :: Developers
Classifier: License :: OSI Approved :: Apache Software License
Classifier: Operating System :: MacOS :: MacOS X
Classifier: Operating System :: POSIX
Classifier: Programming Language :: Python
Classifier: Programming Language :: Python :: 3.7
Classifier: Programming Language :: Python :: 3.8
Classifier: Programming Language :: Python :: 3.9
Classifier: Programming Language :: Python :: 3.10
Classifier: Programming Language :: Python :: 3.11
Classifier: Topic :: Software Development :: Libraries :: Python Modules
License-File: LICENSE
License-File: NOTICE
Requires-Dist: cryptography (>=40.0)
Provides-Extra: tests
Requires-Dist: flake8 ; extra == 'tests'
Requires-Dist: coverage ; extra == 'tests'
Requires-Dist: build ; extra == 'tests'
Requires-Dist: wheel ; extra == 'tests'
Requires-Dist: mypy ; extra == 'tests'
